DEVNOTES.rst
LICENCE
MANIFEST.in
README.rst
dev-requirements.txt
requirements.txt
setup.py
todo.txt
lawvere/__init__.py
lawvere/curry.py
lawvere/dispatcher.py
lawvere/morphism.py
lawvere/signatures.py
lawvere/stack.py
lawvere/typify.py
lawvere.egg-info/PKG-INFO
lawvere.egg-info/SOURCES.txt
lawvere.egg-info/dependency_links.txt
lawvere.egg-info/top_level.txt
lawvere.egg-info/zip-safe
lawvere/tests/__init__.py
lawvere/tests/doc3.py
lawvere/tests/morphism3.py
lawvere/tests/testCurry.py
lawvere/tests/testDispatcher.py
lawvere/tests/testDocExamples.py
lawvere/tests/testMorphism.py
lawvere/tests/testSignatures.py
lawvere/tests/testStack.py
lawvere/tests/testTypify.py