Metadata-Version: 1.1
Name: lawvere
Version: 0.1
Summary: Easy To Use functionnal tool: (de)composition with type checking (curry, arrows), multiple dispatch
Home-page: http://www.python.org/pypi/lawvere
Author: Grégory Salvan
Author-email: apieum@gmail.com
License: LGPL
Platform: UNKNOWN
Classifier: Programming Language :: Python
Classifier: Programming Language :: Python :: 3
Classifier: Development Status :: 1 - Planning
Classifier: Environment :: Other Environment
Classifier: Intended Audience :: Developers
Classifier: License :: OSI Approved :: GNU Library or Lesser General Public License (LGPL)
Classifier: Operating System :: OS Independent
Classifier: Topic :: Software Development :: Libraries :: Python Modules
